coole/__init__.py
coole/main.py
coole-0.0.1.dist-info/METADATA
coole-0.0.1.dist-info/WHEEL
coole-0.0.1.dist-info/entry_points.txt
coole-0.0.1.dist-info/top_level.txt
coole-0.0.1.dist-info/RECORD
