Metadata-Version: 2.4
Name: coole
Version: 0.0.1
Summary: A Python tool to get Google autosuggest keywords.
Author-email: YOUR NAME <you@example.com>
Project-URL: Homepage, https://github.com/pypa/sampleproject
Project-URL: Bug Tracker, https://github.com/pypa/sampleproject/issues
Classifier: Programming Language :: Python :: 3
Classifier: License :: OSI Approved :: MIT License
Classifier: Operating System :: OS Independent
Requires-Python: >=3.7
Requires-Dist: requests
Requires-Dist: rich
